{
  "db_name": "PostgreSQL",
  "query": "\n            SELECT tp.rate_limit_per_second\n            FROM tenant t\n            JOIN tenant_profile tp ON tp.id = t.tenant_profile_id\n            WHERE t.id = $1\n            ",
  "describe": {
    "columns": [
      {
        "ordinal": 0,
        "name": "rate_limit_per_second",
        "type_info": "Int4"
      }
    ],
    "parameters": {
      "Left": [
        "Uuid"
      ]
    },
    "nullable": [
      true
    ]
  },
  "hash": "e082bbd0becb0ed3b50e1c55644588fc113045c8e60023fe4fe078d75e1608ca"
}
