{
  "db_name": "PostgreSQL",
  "query": "DELETE FROM entity_version\n               WHERE entity_id = $1\n                 AND version_number NOT IN (\n                     SELECT version_number FROM entity_version\n                     WHERE entity_id = $1\n                     ORDER BY version_number DESC\n                     LIMIT $2\n                 )",
  "describe": {
    "columns": [],
    "parameters": {
      "Left": [
        "Uuid",
        "Int8"
      ]
    },
    "nullable": []
  },
  "hash": "390be7bed00b50c673c11d19407383dbf158b0c7cebb66bd4e08eb306e971633"
}
